pybary/__init__.py
pybary/pybary.py
pybary-0.2.2.dist-info/LICENSE
pybary-0.2.2.dist-info/METADATA
pybary-0.2.2.dist-info/WHEEL
pybary-0.2.2.dist-info/RECORD
