Metadata-Version: 2.1
Name: pybary
Version: 0.2.2
Summary: Barycenter method in python
Home-page: https://pypi.org/project/pybary/
License: MIT
Keywords: optimization,discrete
Author: Bruno Peixoto
Author-email: brunolnetto@gmail.com
Requires-Python: >=3.9,<3.12
Classifier: Development Status :: 6 - Mature
Classifier: Intended Audience :: Education
Classifier: Intended Audience :: Science/Research
Classifier: License :: OSI Approved :: MIT License
Classifier: Natural Language :: English
Classifier: Programming Language :: Python :: 3
Classifier: Programming Language :: Python :: 3.9
Classifier: Programming Language :: Python :: 3.10
Classifier: Programming Language :: Python :: 3.11
Classifier: Programming Language :: Python :: 3 :: Only
Classifier: Topic :: Scientific/Engineering
Requires-Dist: numpy (==1.24.1)
Project-URL: Repository, https://github.com/asmove/pybary
